easy_biologic/__init__.py
easy_biologic/_version.py
easy_biologic/base_programs.py
easy_biologic/common.py
easy_biologic/device.py
easy_biologic/find_devices.py
easy_biologic/program.py
easy_biologic/techniques_version.json
easy_biologic/lib/__init__.py
easy_biologic/lib/data_parser.py
easy_biologic/lib/ec_errors.py
easy_biologic/lib/ec_find.py
easy_biologic/lib/ec_lib.py
easy_biologic/lib/technique_fields.py
easy_biologic/techniques-5.35/EClib.dll
easy_biologic/techniques-5.35/EClib64.dll
easy_biologic/techniques-5.35/IRcmp.ecc
easy_biologic/techniques-5.35/IRcmp4.ecc
easy_biologic/techniques-5.35/TI.ecc
easy_biologic/techniques-5.35/TI4.ecc
easy_biologic/techniques-5.35/TO.ecc
easy_biologic/techniques-5.35/TO4.ecc
easy_biologic/techniques-5.35/TOS.ecc
easy_biologic/techniques-5.35/TOS4.ecc
easy_biologic/techniques-5.35/Vmp_ii_0437_a6.xlx
easy_biologic/techniques-5.35/Vmp_iv_0395_aa.xlx
easy_biologic/techniques-5.35/biovscan.ecc
easy_biologic/techniques-5.35/blfind.dll
easy_biologic/techniques-5.35/blfind64.dll
easy_biologic/techniques-5.35/ca.ecc
easy_biologic/techniques-5.35/ca4.ecc
easy_biologic/techniques-5.35/calimit.ecc
easy_biologic/techniques-5.35/calimit4.ecc
easy_biologic/techniques-5.35/casg.ecc
easy_biologic/techniques-5.35/casg4.ecc
easy_biologic/techniques-5.35/casp.ecc
easy_biologic/techniques-5.35/casp4.ecc
easy_biologic/techniques-5.35/cp.ecc
easy_biologic/techniques-5.35/cp4.ecc
easy_biologic/techniques-5.35/cplimit.ecc
easy_biologic/techniques-5.35/cplimit4.ecc
easy_biologic/techniques-5.35/cpp.ecc
easy_biologic/techniques-5.35/cpp4.ecc
easy_biologic/techniques-5.35/cv.ecc
easy_biologic/techniques-5.35/cv4.ecc
easy_biologic/techniques-5.35/dnpv.ecc
easy_biologic/techniques-5.35/dnpv4.ecc
easy_biologic/techniques-5.35/dpa.ecc
easy_biologic/techniques-5.35/dpa4.ecc
easy_biologic/techniques-5.35/dpv.ecc
easy_biologic/techniques-5.35/dpv4.ecc
easy_biologic/techniques-5.35/evt.ecc
easy_biologic/techniques-5.35/evt4.ecc
easy_biologic-0.4.0.dist-info/LICENSE
easy_biologic-0.4.0.dist-info/METADATA
easy_biologic-0.4.0.dist-info/WHEEL
easy_biologic-0.4.0.dist-info/top_level.txt
easy_biologic-0.4.0.dist-info/RECORD
