Metadata-Version: 2.1
Name: easy-biologic
Version: 0.4.0
Summary: Controller class for communicating with BioLogic devices.
Home-page: 
Author: Brian Carlsen
Author-email: carlsen.bri@gmail.com
Project-URL: Source Code, https://github.com/bicarlsen/easy-biologic
Project-URL: Bug Tracker, https://github.com/bicarlsen/easy-biologic/issues
Keywords: biologic
Classifier: Programming Language :: Python :: 3
Classifier: License :: OSI Approved :: GNU General Public License v3 (GPLv3)
Classifier: Operating System :: Microsoft :: Windows
Classifier: Development Status :: 3 - Alpha
Requires-Python: >=3.7
License-File: LICENSE
Provides-Extra: pandas
Requires-Dist: pandas ; extra == 'pandas'
